iplocation.py
setup.py
iplocation.egg-info/PKG-INFO
iplocation.egg-info/SOURCES.txt
iplocation.egg-info/dependency_links.txt
iplocation.egg-info/requires.txt
iplocation.egg-info/top_level.txt