Metadata-Version: 1.0
Name: iplocation
Version: 0.1
Summary: Return city, country, location, business details of given/outgoing ip
Home-page: https://github.com/mrahma01/iplocation
Author: Muhammad M Rahman
Author-email: mmrs151@gmail.com
License: GPL
Keywords: iptolocaiton geoip
Platform: UNKNOWN
Classifier: License :: OSI Approved :: GNU General Public License (GPL)
Classifier: Programming Language :: Python
Classifier: Development Status :: 4 - Beta
Classifier: Intended Audience :: Developers
Classifier: Topic :: Internet
